pyclick/__init__.py
pyclick/admin.py
pyclick/apps.py
pyclick/authorization.py
pyclick/methods_merchant_api.py
pyclick/models.py
pyclick/serializers.py
pyclick/status.py
pyclick/urls.py
pyclick/utils.py
pyclick/views.py
pyclick/migrations/0001_initial.py
pyclick/migrations/__init__.py
python_click-0.1.4.dist-info/LICENSE
python_click-0.1.4.dist-info/METADATA
python_click-0.1.4.dist-info/WHEEL
python_click-0.1.4.dist-info/top_level.txt
python_click-0.1.4.dist-info/RECORD
