Metadata-Version: 2.1
Name: python-click
Version: 0.1.4
Summary: Этот пакет позволяет легко интегрировать платежную систему Click через фреймворк Django в Python
Home-page: https://github.com/yakubov9791999/python-click
Author: Sirojiddin Yakubov
Author-email: yakubov9791999@gmail.com
License: UNKNOWN
Project-URL: Source, https://github.com/yakubov9791999/python-click
Keywords: python,click,django,django rest framework,requests,python-click,pyclick,yakubov9791999,Sirojiddin Yakubov,Yakubov Developer
Platform: UNKNOWN
Classifier: Development Status :: 5 - Production/Stable
Classifier: Environment :: Web Environment
Classifier: Framework :: Django
Classifier: Framework :: Django :: 3.0
Classifier: Framework :: Django :: 3.1
Classifier: Framework :: Django :: 3.2
Classifier: Framework :: Django :: 4.0
Classifier: Framework :: Django :: 4.1
Classifier: Intended Audience :: Developers
Classifier: License :: OSI Approved :: MIT License
Classifier: Operating System :: OS Independent
Classifier: Programming Language :: Python
Classifier: Programming Language :: Python :: 3
Classifier: Programming Language :: Python :: 3.6
Classifier: Programming Language :: Python :: 3.7
Classifier: Programming Language :: Python :: 3.8
Classifier: Programming Language :: Python :: 3.9
Classifier: Programming Language :: Python :: 3.10
Classifier: Programming Language :: Python :: 3 :: Only
Classifier: Topic :: Internet :: WWW/HTTP
Requires-Python: >=3.6
License-File: LICENSE
